{
  "reference": "PSA 51:20",
  "book": "PSA",
  "book_code": "PSA",
  "chapter": 51,
  "verse": 20,
  "tokens": [
    {
      "surface": "הֵיטִ֣יבָ/ה",
      "lemma": "",
      "translit": "",
      "gloss": "",
      "morph": "HVhv2ms/Sh",
      "strong": "3190",
      "index": 1,
      "resolved_lemma": "",
      "resolved_translit": "",
      "resolved_gloss": "to be (causative) make well, literally (sound, beautiful) or figuratively (happy, successful, right)",
      "translation": "to be (causative) make well, literally (sound, beautiful) or figuratively (happy, successful, right)"
    },
    {
      "surface": "הֵיטִ֣יבָ/ה",
      "lemma": "",
      "translit": "",
      "gloss": "",
      "morph": "HVhv2ms/Sh",
      "strong": "3190",
      "index": 1,
      "resolved_lemma": "",
      "resolved_translit": "",
      "resolved_gloss": "to be (causative) make well, literally (sound, beautiful) or figuratively (happy, successful, right)",
      "translation": "to be (causative) make well, literally (sound, beautiful) or figuratively (happy, successful, right)"
    },
    {
      "surface": "בִ֭/רְצוֹנְ/ךָ",
      "lemma": "",
      "translit": "",
      "gloss": "",
      "morph": "HR/Ncmsc/Sp2ms",
      "strong": "b/7522",
      "index": 2,
      "resolved_lemma": "",
      "resolved_translit": "",
      "resolved_gloss": "delight (especially as shown)",
      "translation": "delight (especially as shown)"
    },
    {
      "surface": "בִ֭/רְצוֹנְ/ךָ",
      "lemma": "",
      "translit": "",
      "gloss": "",
      "morph": "HR/Ncmsc/Sp2ms",
      "strong": "b/7522",
      "index": 2,
      "resolved_lemma": "",
      "resolved_translit": "",
      "resolved_gloss": "delight (especially as shown)",
      "translation": "delight (especially as shown)"
    },
    {
      "surface": "אֶת",
      "lemma": "",
      "translit": "",
      "gloss": "",
      "morph": "HTo",
      "strong": "853",
      "index": 3,
      "resolved_lemma": "",
      "resolved_translit": "",
      "resolved_gloss": "properly, self (but generally used to point out more definitely the object of a verb or preposition, even or namely)",
      "translation": "properly, self (but generally used to point out more definitely the object of a verb or preposition, even or namely)"
    },
    {
      "surface": "אֶת",
      "lemma": "",
      "translit": "",
      "gloss": "",
      "morph": "HTo",
      "strong": "853",
      "index": 3,
      "resolved_lemma": "",
      "resolved_translit": "",
      "resolved_gloss": "properly, self (but generally used to point out more definitely the object of a verb or preposition, even or namely)",
      "translation": "properly, self (but generally used to point out more definitely the object of a verb or preposition, even or namely)"
    },
    {
      "surface": "צִיּ֑וֹן",
      "lemma": "",
      "translit": "",
      "gloss": "",
      "morph": "HNp",
      "strong": "6726",
      "index": 4,
      "resolved_lemma": "",
      "resolved_translit": "",
      "resolved_gloss": "Tsijon (as a permanent capital), a mountain of Jerusalem",
      "translation": "Tsijon (as a permanent capital), a mountain of Jerusalem"
    },
    {
      "surface": "צִיּ֑וֹן",
      "lemma": "",
      "translit": "",
      "gloss": "",
      "morph": "HNp",
      "strong": "6726",
      "index": 4,
      "resolved_lemma": "",
      "resolved_translit": "",
      "resolved_gloss": "Tsijon (as a permanent capital), a mountain of Jerusalem",
      "translation": "Tsijon (as a permanent capital), a mountain of Jerusalem"
    },
    {
      "surface": "תִּ֝בְנֶ֗ה",
      "lemma": "",
      "translit": "",
      "gloss": "",
      "morph": "HVqi2ms",
      "strong": "1129",
      "index": 5,
      "resolved_lemma": "",
      "resolved_translit": "",
      "resolved_gloss": "to build (literally and figuratively)",
      "translation": "to build (literally and figuratively)"
    },
    {
      "surface": "תִּ֝בְנֶ֗ה",
      "lemma": "",
      "translit": "",
      "gloss": "",
      "morph": "HVqi2ms",
      "strong": "1129",
      "index": 5,
      "resolved_lemma": "",
      "resolved_translit": "",
      "resolved_gloss": "to build (literally and figuratively)",
      "translation": "to build (literally and figuratively)"
    },
    {
      "surface": "חוֹמ֥וֹת",
      "lemma": "",
      "translit": "",
      "gloss": "",
      "morph": "HNcfpc",
      "strong": "2346",
      "index": 6,
      "resolved_lemma": "",
      "resolved_translit": "",
      "resolved_gloss": "a wall of protection",
      "translation": "a wall of protection"
    },
    {
      "surface": "חוֹמ֥וֹת",
      "lemma": "",
      "translit": "",
      "gloss": "",
      "morph": "HNcfpc",
      "strong": "2346",
      "index": 6,
      "resolved_lemma": "",
      "resolved_translit": "",
      "resolved_gloss": "a wall of protection",
      "translation": "a wall of protection"
    },
    {
      "surface": "יְרוּשָׁלִָֽם",
      "lemma": "",
      "translit": "",
      "gloss": "",
      "morph": "HNp",
      "strong": "3389",
      "index": 7,
      "resolved_lemma": "",
      "resolved_translit": "",
      "resolved_gloss": "Jerushalaim or Jerushalem, the capital city of Palestine",
      "translation": "Jerushalaim or Jerushalem, the capital city of Palestine"
    },
    {
      "surface": "יְרוּשָׁלִָֽם",
      "lemma": "",
      "translit": "",
      "gloss": "",
      "morph": "HNp",
      "strong": "3389",
      "index": 7,
      "resolved_lemma": "",
      "resolved_translit": "",
      "resolved_gloss": "Jerushalaim or Jerushalem, the capital city of Palestine",
      "translation": "Jerushalaim or Jerushalem, the capital city of Palestine"
    }
  ]
}