{
  "reference": "EXO 22:18",
  "book": "EXO",
  "book_code": "EXO",
  "chapter": 22,
  "verse": 18,
  "tokens": [
    {
      "surface": "כָּל",
      "lemma": "",
      "translit": "",
      "gloss": "",
      "morph": "HNcmsc",
      "strong": "3605",
      "index": 1,
      "resolved_lemma": "",
      "resolved_translit": "",
      "resolved_gloss": "properly, the whole; hence, all, any or every (in the singular only, but often in a plural sense)",
      "translation": "properly, the whole; hence, all, any or every (in the singular only, but often in a plural sense)"
    },
    {
      "surface": "כָּל",
      "lemma": "",
      "translit": "",
      "gloss": "",
      "morph": "HNcmsc",
      "strong": "3605",
      "index": 1,
      "resolved_lemma": "",
      "resolved_translit": "",
      "resolved_gloss": "properly, the whole; hence, all, any or every (in the singular only, but often in a plural sense)",
      "translation": "properly, the whole; hence, all, any or every (in the singular only, but often in a plural sense)"
    },
    {
      "surface": "שֹׁכֵ֥ב",
      "lemma": "",
      "translit": "",
      "gloss": "",
      "morph": "HVqrmsa",
      "strong": "7901",
      "index": 2,
      "resolved_lemma": "",
      "resolved_translit": "",
      "resolved_gloss": "to lie down (for rest, sexual connection, decease or any other purpose)",
      "translation": "to lie down (for rest, sexual connection, decease or any other purpose)"
    },
    {
      "surface": "שֹׁכֵ֥ב",
      "lemma": "",
      "translit": "",
      "gloss": "",
      "morph": "HVqrmsa",
      "strong": "7901",
      "index": 2,
      "resolved_lemma": "",
      "resolved_translit": "",
      "resolved_gloss": "to lie down (for rest, sexual connection, decease or any other purpose)",
      "translation": "to lie down (for rest, sexual connection, decease or any other purpose)"
    },
    {
      "surface": "עִם",
      "lemma": "",
      "translit": "",
      "gloss": "",
      "morph": "HR",
      "strong": "5973 a",
      "index": 3,
      "resolved_lemma": "",
      "resolved_translit": "",
      "resolved_gloss": "adverb or preposition, with (i.e. in conjunction with), in varied applications; specifically, equally with; often with prepositional prefix (and then usually unrepresented in English)",
      "translation": "adverb or preposition, with (i.e. in conjunction with), in varied applications; specifically, equally with; often with prepositional prefix (and then usually unrepresented in English)"
    },
    {
      "surface": "עִם",
      "lemma": "",
      "translit": "",
      "gloss": "",
      "morph": "HR",
      "strong": "5973 a",
      "index": 3,
      "resolved_lemma": "",
      "resolved_translit": "",
      "resolved_gloss": "adverb or preposition, with (i.e. in conjunction with), in varied applications; specifically, equally with; often with prepositional prefix (and then usually unrepresented in English)",
      "translation": "adverb or preposition, with (i.e. in conjunction with), in varied applications; specifically, equally with; often with prepositional prefix (and then usually unrepresented in English)"
    },
    {
      "surface": "בְּהֵמָ֖ה",
      "lemma": "",
      "translit": "",
      "gloss": "",
      "morph": "HNcfsa",
      "strong": "929",
      "index": 4,
      "resolved_lemma": "",
      "resolved_translit": "",
      "resolved_gloss": "properly, a dumb beast; especially any large quadruped or animal (often collective)",
      "translation": "properly, a dumb beast; especially any large quadruped or animal (often collective)"
    },
    {
      "surface": "בְּהֵמָ֖ה",
      "lemma": "",
      "translit": "",
      "gloss": "",
      "morph": "HNcfsa",
      "strong": "929",
      "index": 4,
      "resolved_lemma": "",
      "resolved_translit": "",
      "resolved_gloss": "properly, a dumb beast; especially any large quadruped or animal (often collective)",
      "translation": "properly, a dumb beast; especially any large quadruped or animal (often collective)"
    },
    {
      "surface": "מ֥וֹת",
      "lemma": "",
      "translit": "",
      "gloss": "",
      "morph": "HVqa",
      "strong": "4191",
      "index": 5,
      "resolved_lemma": "",
      "resolved_translit": "",
      "resolved_gloss": "to die (literally or figuratively); causatively, to kill",
      "translation": "to die (literally or figuratively); causatively, to kill"
    },
    {
      "surface": "מ֥וֹת",
      "lemma": "",
      "translit": "",
      "gloss": "",
      "morph": "HVqa",
      "strong": "4191",
      "index": 5,
      "resolved_lemma": "",
      "resolved_translit": "",
      "resolved_gloss": "to die (literally or figuratively); causatively, to kill",
      "translation": "to die (literally or figuratively); causatively, to kill"
    },
    {
      "surface": "יוּמָֽת",
      "lemma": "",
      "translit": "",
      "gloss": "",
      "morph": "HVHi3ms",
      "strong": "4191",
      "index": 6,
      "resolved_lemma": "",
      "resolved_translit": "",
      "resolved_gloss": "to die (literally or figuratively); causatively, to kill",
      "translation": "to die (literally or figuratively); causatively, to kill"
    },
    {
      "surface": "יוּמָֽת",
      "lemma": "",
      "translit": "",
      "gloss": "",
      "morph": "HVHi3ms",
      "strong": "4191",
      "index": 6,
      "resolved_lemma": "",
      "resolved_translit": "",
      "resolved_gloss": "to die (literally or figuratively); causatively, to kill",
      "translation": "to die (literally or figuratively); causatively, to kill"
    }
  ]
}