{
  "reference": "PSA 107:39",
  "book": "PSA",
  "book_code": "PSA",
  "chapter": 107,
  "verse": 39,
  "tokens": [
    {
      "surface": "וַ/יִּמְעֲט֥וּ",
      "lemma": "",
      "translit": "",
      "gloss": "",
      "morph": "HC/Vqw3mp",
      "strong": "c/4591",
      "index": 1,
      "resolved_lemma": "",
      "resolved_translit": "",
      "resolved_gloss": "properly, to pare off, i.e. lessen; intransitively, to be (or causatively, to make) small or few (or figuratively, ineffective)",
      "translation": "properly, to pare off, i.e. lessen; intransitively, to be (or causatively, to make) small or few (or figuratively, ineffective)"
    },
    {
      "surface": "וַ/יִּמְעֲט֥וּ",
      "lemma": "",
      "translit": "",
      "gloss": "",
      "morph": "HC/Vqw3mp",
      "strong": "c/4591",
      "index": 1,
      "resolved_lemma": "",
      "resolved_translit": "",
      "resolved_gloss": "properly, to pare off, i.e. lessen; intransitively, to be (or causatively, to make) small or few (or figuratively, ineffective)",
      "translation": "properly, to pare off, i.e. lessen; intransitively, to be (or causatively, to make) small or few (or figuratively, ineffective)"
    },
    {
      "surface": "וַ/יָּשֹׁ֑חוּ",
      "lemma": "",
      "translit": "",
      "gloss": "",
      "morph": "HC/Vqw3mp",
      "strong": "c/7817",
      "index": 2,
      "resolved_lemma": "",
      "resolved_translit": "",
      "resolved_gloss": "to sink or depress (reflexive or causative)",
      "translation": "to sink or depress (reflexive or causative)"
    },
    {
      "surface": "וַ/יָּשֹׁ֑חוּ",
      "lemma": "",
      "translit": "",
      "gloss": "",
      "morph": "HC/Vqw3mp",
      "strong": "c/7817",
      "index": 2,
      "resolved_lemma": "",
      "resolved_translit": "",
      "resolved_gloss": "to sink or depress (reflexive or causative)",
      "translation": "to sink or depress (reflexive or causative)"
    },
    {
      "surface": "מֵ/עֹ֖צֶר",
      "lemma": "",
      "translit": "",
      "gloss": "",
      "morph": "HR/Ncmsc",
      "strong": "m/6115",
      "index": 3,
      "resolved_lemma": "",
      "resolved_translit": "",
      "resolved_gloss": "closure; also constraint",
      "translation": "closure; also constraint"
    },
    {
      "surface": "מֵ/עֹ֖צֶר",
      "lemma": "",
      "translit": "",
      "gloss": "",
      "morph": "HR/Ncmsc",
      "strong": "m/6115",
      "index": 3,
      "resolved_lemma": "",
      "resolved_translit": "",
      "resolved_gloss": "closure; also constraint",
      "translation": "closure; also constraint"
    },
    {
      "surface": "רָעָ֣ה",
      "lemma": "",
      "translit": "",
      "gloss": "",
      "morph": "HNcfsa",
      "strong": "7451 c",
      "index": 4,
      "resolved_lemma": "",
      "resolved_translit": "",
      "resolved_gloss": "bad or (as noun) evil (natural or moral)",
      "translation": "bad or (as noun) evil (natural or moral)"
    },
    {
      "surface": "רָעָ֣ה",
      "lemma": "",
      "translit": "",
      "gloss": "",
      "morph": "HNcfsa",
      "strong": "7451 c",
      "index": 4,
      "resolved_lemma": "",
      "resolved_translit": "",
      "resolved_gloss": "bad or (as noun) evil (natural or moral)",
      "translation": "bad or (as noun) evil (natural or moral)"
    },
    {
      "surface": "וְ/יָגֽוֹן",
      "lemma": "",
      "translit": "",
      "gloss": "",
      "morph": "HC/Ncmsa",
      "strong": "c/3015",
      "index": 5,
      "resolved_lemma": "",
      "resolved_translit": "",
      "resolved_gloss": "affliction",
      "translation": "affliction"
    },
    {
      "surface": "וְ/יָגֽוֹן",
      "lemma": "",
      "translit": "",
      "gloss": "",
      "morph": "HC/Ncmsa",
      "strong": "c/3015",
      "index": 5,
      "resolved_lemma": "",
      "resolved_translit": "",
      "resolved_gloss": "affliction",
      "translation": "affliction"
    }
  ]
}