{
  "reference": "2CH 25:11",
  "book": "2CH",
  "book_code": "2CH",
  "chapter": 25,
  "verse": 11,
  "tokens": [
    {
      "surface": "וַ/אֲמַצְיָ֨הוּ֙",
      "lemma": "",
      "translit": "",
      "gloss": "",
      "morph": "HC/Np",
      "strong": "c/558",
      "index": 1,
      "resolved_lemma": "",
      "resolved_translit": "",
      "resolved_gloss": "Amatsjah, the name of four Israelites",
      "translation": "Amatsjah, the name of four Israelites"
    },
    {
      "surface": "וַ/אֲמַצְיָ֨הוּ֙",
      "lemma": "",
      "translit": "",
      "gloss": "",
      "morph": "HC/Np",
      "strong": "c/558",
      "index": 1,
      "resolved_lemma": "",
      "resolved_translit": "",
      "resolved_gloss": "Amatsjah, the name of four Israelites",
      "translation": "Amatsjah, the name of four Israelites"
    },
    {
      "surface": "הִתְחַזַּ֔ק",
      "lemma": "",
      "translit": "",
      "gloss": "",
      "morph": "HVtp3ms",
      "strong": "2388",
      "index": 2,
      "resolved_lemma": "",
      "resolved_translit": "",
      "resolved_gloss": "to fasten upon; hence, to seize, be strong (figuratively, courageous, causatively strengthen, cure, help, repair, fortify), obstinate; to bind, restrain, conquer",
      "translation": "to fasten upon; hence, to seize, be strong (figuratively, courageous, causatively strengthen, cure, help, repair, fortify), obstinate; to bind, restrain, conquer"
    },
    {
      "surface": "הִתְחַזַּ֔ק",
      "lemma": "",
      "translit": "",
      "gloss": "",
      "morph": "HVtp3ms",
      "strong": "2388",
      "index": 2,
      "resolved_lemma": "",
      "resolved_translit": "",
      "resolved_gloss": "to fasten upon; hence, to seize, be strong (figuratively, courageous, causatively strengthen, cure, help, repair, fortify), obstinate; to bind, restrain, conquer",
      "translation": "to fasten upon; hence, to seize, be strong (figuratively, courageous, causatively strengthen, cure, help, repair, fortify), obstinate; to bind, restrain, conquer"
    },
    {
      "surface": "וַ/יִּנְהַג֙",
      "lemma": "",
      "translit": "",
      "gloss": "",
      "morph": "HC/Vqw3ms",
      "strong": "c/5090 a",
      "index": 3,
      "resolved_lemma": "",
      "resolved_translit": "",
      "resolved_gloss": "to drive forth (a person, an animal or chariot), i.e. lead, carry away; reflexively, to proceed (i.e. impel or guide oneself); also (from the panting induced by effort), to sigh",
      "translation": "to drive forth (a person, an animal or chariot), i.e. lead, carry away; reflexively, to proceed (i.e. impel or guide oneself); also (from the panting induced by effort), to sigh"
    },
    {
      "surface": "וַ/יִּנְהַג֙",
      "lemma": "",
      "translit": "",
      "gloss": "",
      "morph": "HC/Vqw3ms",
      "strong": "c/5090 a",
      "index": 3,
      "resolved_lemma": "",
      "resolved_translit": "",
      "resolved_gloss": "to drive forth (a person, an animal or chariot), i.e. lead, carry away; reflexively, to proceed (i.e. impel or guide oneself); also (from the panting induced by effort), to sigh",
      "translation": "to drive forth (a person, an animal or chariot), i.e. lead, carry away; reflexively, to proceed (i.e. impel or guide oneself); also (from the panting induced by effort), to sigh"
    },
    {
      "surface": "אֶת",
      "lemma": "",
      "translit": "",
      "gloss": "",
      "morph": "HTo",
      "strong": "853",
      "index": 4,
      "resolved_lemma": "",
      "resolved_translit": "",
      "resolved_gloss": "properly, self (but generally used to point out more definitely the object of a verb or preposition, even or namely)",
      "translation": "properly, self (but generally used to point out more definitely the object of a verb or preposition, even or namely)"
    },
    {
      "surface": "אֶת",
      "lemma": "",
      "translit": "",
      "gloss": "",
      "morph": "HTo",
      "strong": "853",
      "index": 4,
      "resolved_lemma": "",
      "resolved_translit": "",
      "resolved_gloss": "properly, self (but generally used to point out more definitely the object of a verb or preposition, even or namely)",
      "translation": "properly, self (but generally used to point out more definitely the object of a verb or preposition, even or namely)"
    },
    {
      "surface": "עַמּ֔/וֹ",
      "lemma": "",
      "translit": "",
      "gloss": "",
      "morph": "HNcmsc/Sp3ms",
      "strong": "5971 a",
      "index": 5,
      "resolved_lemma": "",
      "resolved_translit": "",
      "resolved_gloss": "a people (as a congregated unit); specifically, a tribe (as those of Israel); hence (collectively) troops or attendants; figuratively, a flock",
      "translation": "a people (as a congregated unit); specifically, a tribe (as those of Israel); hence (collectively) troops or attendants; figuratively, a flock"
    },
    {
      "surface": "עַמּ֔/וֹ",
      "lemma": "",
      "translit": "",
      "gloss": "",
      "morph": "HNcmsc/Sp3ms",
      "strong": "5971 a",
      "index": 5,
      "resolved_lemma": "",
      "resolved_translit": "",
      "resolved_gloss": "a people (as a congregated unit); specifically, a tribe (as those of Israel); hence (collectively) troops or attendants; figuratively, a flock",
      "translation": "a people (as a congregated unit); specifically, a tribe (as those of Israel); hence (collectively) troops or attendants; figuratively, a flock"
    },
    {
      "surface": "וַ/יֵּ֖לֶךְ",
      "lemma": "",
      "translit": "",
      "gloss": "",
      "morph": "HC/Vqw3ms",
      "strong": "c/3212",
      "index": 6,
      "resolved_lemma": "",
      "resolved_translit": "",
      "resolved_gloss": "to walk (literally or figuratively); causatively, to carry (in various senses)",
      "translation": "to walk (literally or figuratively); causatively, to carry (in various senses)"
    },
    {
      "surface": "וַ/יֵּ֖לֶךְ",
      "lemma": "",
      "translit": "",
      "gloss": "",
      "morph": "HC/Vqw3ms",
      "strong": "c/3212",
      "index": 6,
      "resolved_lemma": "",
      "resolved_translit": "",
      "resolved_gloss": "to walk (literally or figuratively); causatively, to carry (in various senses)",
      "translation": "to walk (literally or figuratively); causatively, to carry (in various senses)"
    },
    {
      "surface": "גֵּ֣יא",
      "lemma": "",
      "translit": "",
      "gloss": "",
      "morph": "HNp",
      "strong": "1516",
      "index": 7,
      "resolved_lemma": "",
      "resolved_translit": "",
      "resolved_gloss": "a gorge (from its lofty sides; hence, narrow, but not a gully or winter-torrent)",
      "translation": "a gorge (from its lofty sides; hence, narrow, but not a gully or winter-torrent)"
    },
    {
      "surface": "גֵּ֣יא",
      "lemma": "",
      "translit": "",
      "gloss": "",
      "morph": "HNp",
      "strong": "1516",
      "index": 7,
      "resolved_lemma": "",
      "resolved_translit": "",
      "resolved_gloss": "a gorge (from its lofty sides; hence, narrow, but not a gully or winter-torrent)",
      "translation": "a gorge (from its lofty sides; hence, narrow, but not a gully or winter-torrent)"
    },
    {
      "surface": "הַמֶּ֑לַח",
      "lemma": "",
      "translit": "",
      "gloss": "",
      "morph": "HNp",
      "strong": "4417",
      "index": 8,
      "resolved_lemma": "",
      "resolved_translit": "",
      "resolved_gloss": "properly, powder, i.e. (specifically) salt (as easily pulverized and dissolved)",
      "translation": "properly, powder, i.e. (specifically) salt (as easily pulverized and dissolved)"
    },
    {
      "surface": "הַמֶּ֑לַח",
      "lemma": "",
      "translit": "",
      "gloss": "",
      "morph": "HNp",
      "strong": "4417",
      "index": 8,
      "resolved_lemma": "",
      "resolved_translit": "",
      "resolved_gloss": "properly, powder, i.e. (specifically) salt (as easily pulverized and dissolved)",
      "translation": "properly, powder, i.e. (specifically) salt (as easily pulverized and dissolved)"
    },
    {
      "surface": "וַ/יַּ֥ךְ",
      "lemma": "",
      "translit": "",
      "gloss": "",
      "morph": "HC/Vhw3ms",
      "strong": "c/5221",
      "index": 9,
      "resolved_lemma": "",
      "resolved_translit": "",
      "resolved_gloss": "to strike (lightly or severely, literally or figuratively)",
      "translation": "to strike (lightly or severely, literally or figuratively)"
    },
    {
      "surface": "וַ/יַּ֥ךְ",
      "lemma": "",
      "translit": "",
      "gloss": "",
      "morph": "HC/Vhw3ms",
      "strong": "c/5221",
      "index": 9,
      "resolved_lemma": "",
      "resolved_translit": "",
      "resolved_gloss": "to strike (lightly or severely, literally or figuratively)",
      "translation": "to strike (lightly or severely, literally or figuratively)"
    },
    {
      "surface": "אֶת",
      "lemma": "",
      "translit": "",
      "gloss": "",
      "morph": "HTo",
      "strong": "853",
      "index": 10,
      "resolved_lemma": "",
      "resolved_translit": "",
      "resolved_gloss": "properly, self (but generally used to point out more definitely the object of a verb or preposition, even or namely)",
      "translation": "properly, self (but generally used to point out more definitely the object of a verb or preposition, even or namely)"
    },
    {
      "surface": "אֶת",
      "lemma": "",
      "translit": "",
      "gloss": "",
      "morph": "HTo",
      "strong": "853",
      "index": 10,
      "resolved_lemma": "",
      "resolved_translit": "",
      "resolved_gloss": "properly, self (but generally used to point out more definitely the object of a verb or preposition, even or namely)",
      "translation": "properly, self (but generally used to point out more definitely the object of a verb or preposition, even or namely)"
    },
    {
      "surface": "בְּנֵי",
      "lemma": "",
      "translit": "",
      "gloss": "",
      "morph": "HNcmpc",
      "strong": "1121 a",
      "index": 11,
      "resolved_lemma": "",
      "resolved_translit": "",
      "resolved_gloss": "a son (as a builder of the family name), in the widest sense (of literal and figurative relationship, including grandson, subject, nation, quality or condition, etc., (like father or brother), etc.)",
      "translation": "a son (as a builder of the family name), in the widest sense (of literal and figurative relationship, including grandson, subject, nation, quality or condition, etc., (like father or brother), etc.)"
    },
    {
      "surface": "בְּנֵי",
      "lemma": "",
      "translit": "",
      "gloss": "",
      "morph": "HNcmpc",
      "strong": "1121 a",
      "index": 11,
      "resolved_lemma": "",
      "resolved_translit": "",
      "resolved_gloss": "a son (as a builder of the family name), in the widest sense (of literal and figurative relationship, including grandson, subject, nation, quality or condition, etc., (like father or brother), etc.)",
      "translation": "a son (as a builder of the family name), in the widest sense (of literal and figurative relationship, including grandson, subject, nation, quality or condition, etc., (like father or brother), etc.)"
    },
    {
      "surface": "שֵׂעִ֖יר",
      "lemma": "",
      "translit": "",
      "gloss": "",
      "morph": "HNp",
      "strong": "8165 a",
      "index": 12,
      "resolved_lemma": "",
      "resolved_translit": "",
      "resolved_gloss": "Seir, a mountain of Idumaea and its aboriginal occupants, also one in Palestine",
      "translation": "Seir, a mountain of Idumaea and its aboriginal occupants, also one in Palestine"
    },
    {
      "surface": "שֵׂעִ֖יר",
      "lemma": "",
      "translit": "",
      "gloss": "",
      "morph": "HNp",
      "strong": "8165 a",
      "index": 12,
      "resolved_lemma": "",
      "resolved_translit": "",
      "resolved_gloss": "Seir, a mountain of Idumaea and its aboriginal occupants, also one in Palestine",
      "translation": "Seir, a mountain of Idumaea and its aboriginal occupants, also one in Palestine"
    },
    {
      "surface": "עֲשֶׂ֥רֶת",
      "lemma": "",
      "translit": "",
      "gloss": "",
      "morph": "HAcmsc",
      "strong": "6235",
      "index": 13,
      "resolved_lemma": "",
      "resolved_translit": "",
      "resolved_gloss": "ten (as an accumulation to the extent of the digits)",
      "translation": "ten (as an accumulation to the extent of the digits)"
    },
    {
      "surface": "עֲשֶׂ֥רֶת",
      "lemma": "",
      "translit": "",
      "gloss": "",
      "morph": "HAcmsc",
      "strong": "6235",
      "index": 13,
      "resolved_lemma": "",
      "resolved_translit": "",
      "resolved_gloss": "ten (as an accumulation to the extent of the digits)",
      "translation": "ten (as an accumulation to the extent of the digits)"
    },
    {
      "surface": "אֲלָפִֽים",
      "lemma": "",
      "translit": "",
      "gloss": "",
      "morph": "HAcbpa",
      "strong": "505",
      "index": 14,
      "resolved_lemma": "",
      "resolved_translit": "",
      "resolved_gloss": "hence (the ox's head being the first letter of the alphabet, and this eventually used as a numeral) a thousand",
      "translation": "hence (the ox's head being the first letter of the alphabet, and this eventually used as a numeral) a thousand"
    },
    {
      "surface": "אֲלָפִֽים",
      "lemma": "",
      "translit": "",
      "gloss": "",
      "morph": "HAcbpa",
      "strong": "505",
      "index": 14,
      "resolved_lemma": "",
      "resolved_translit": "",
      "resolved_gloss": "hence (the ox's head being the first letter of the alphabet, and this eventually used as a numeral) a thousand",
      "translation": "hence (the ox's head being the first letter of the alphabet, and this eventually used as a numeral) a thousand"
    }
  ]
}