{
  "reference": "DAN 10:9",
  "book": "DAN",
  "book_code": "DAN",
  "chapter": 10,
  "verse": 9,
  "tokens": [
    {
      "surface": "וָ/אֶשְׁמַ֖ע",
      "lemma": "",
      "translit": "",
      "gloss": "",
      "morph": "HC/Vqw1cs",
      "strong": "c/8085",
      "index": 1,
      "resolved_lemma": "",
      "resolved_translit": "",
      "resolved_gloss": "to hear intelligently (often with implication of attention, obedience, etc.; causatively, to tell, etc.)",
      "translation": "to hear intelligently (often with implication of attention, obedience, etc.; causatively, to tell, etc.)"
    },
    {
      "surface": "וָ/אֶשְׁמַ֖ע",
      "lemma": "",
      "translit": "",
      "gloss": "",
      "morph": "HC/Vqw1cs",
      "strong": "c/8085",
      "index": 1,
      "resolved_lemma": "",
      "resolved_translit": "",
      "resolved_gloss": "to hear intelligently (often with implication of attention, obedience, etc.; causatively, to tell, etc.)",
      "translation": "to hear intelligently (often with implication of attention, obedience, etc.; causatively, to tell, etc.)"
    },
    {
      "surface": "אֶת",
      "lemma": "",
      "translit": "",
      "gloss": "",
      "morph": "HTo",
      "strong": "853",
      "index": 2,
      "resolved_lemma": "",
      "resolved_translit": "",
      "resolved_gloss": "properly, self (but generally used to point out more definitely the object of a verb or preposition, even or namely)",
      "translation": "properly, self (but generally used to point out more definitely the object of a verb or preposition, even or namely)"
    },
    {
      "surface": "אֶת",
      "lemma": "",
      "translit": "",
      "gloss": "",
      "morph": "HTo",
      "strong": "853",
      "index": 2,
      "resolved_lemma": "",
      "resolved_translit": "",
      "resolved_gloss": "properly, self (but generally used to point out more definitely the object of a verb or preposition, even or namely)",
      "translation": "properly, self (but generally used to point out more definitely the object of a verb or preposition, even or namely)"
    },
    {
      "surface": "ק֣וֹל",
      "lemma": "",
      "translit": "",
      "gloss": "",
      "morph": "HNcmsc",
      "strong": "6963 a",
      "index": 3,
      "resolved_lemma": "",
      "resolved_translit": "",
      "resolved_gloss": "a voice or sound",
      "translation": "a voice or sound"
    },
    {
      "surface": "ק֣וֹל",
      "lemma": "",
      "translit": "",
      "gloss": "",
      "morph": "HNcmsc",
      "strong": "6963 a",
      "index": 3,
      "resolved_lemma": "",
      "resolved_translit": "",
      "resolved_gloss": "a voice or sound",
      "translation": "a voice or sound"
    },
    {
      "surface": "דְּבָרָ֑י/ו",
      "lemma": "",
      "translit": "",
      "gloss": "",
      "morph": "HNcmpc/Sp3ms",
      "strong": "1697",
      "index": 4,
      "resolved_lemma": "",
      "resolved_translit": "",
      "resolved_gloss": "a word; by implication, a matter (as spoken of) or thing; adverbially, a cause",
      "translation": "a word; by implication, a matter (as spoken of) or thing; adverbially, a cause"
    },
    {
      "surface": "דְּבָרָ֑י/ו",
      "lemma": "",
      "translit": "",
      "gloss": "",
      "morph": "HNcmpc/Sp3ms",
      "strong": "1697",
      "index": 4,
      "resolved_lemma": "",
      "resolved_translit": "",
      "resolved_gloss": "a word; by implication, a matter (as spoken of) or thing; adverbially, a cause",
      "translation": "a word; by implication, a matter (as spoken of) or thing; adverbially, a cause"
    },
    {
      "surface": "וּ/כְ/שָׁמְעִ/י֙",
      "lemma": "",
      "translit": "",
      "gloss": "",
      "morph": "HC/R/Vqc/Sp1cs",
      "strong": "c/k/8085",
      "index": 5,
      "resolved_lemma": "",
      "resolved_translit": "",
      "resolved_gloss": "to hear intelligently (often with implication of attention, obedience, etc.; causatively, to tell, etc.)",
      "translation": "to hear intelligently (often with implication of attention, obedience, etc.; causatively, to tell, etc.)"
    },
    {
      "surface": "וּ/כְ/שָׁמְעִ/י֙",
      "lemma": "",
      "translit": "",
      "gloss": "",
      "morph": "HC/R/Vqc/Sp1cs",
      "strong": "c/k/8085",
      "index": 5,
      "resolved_lemma": "",
      "resolved_translit": "",
      "resolved_gloss": "to hear intelligently (often with implication of attention, obedience, etc.; causatively, to tell, etc.)",
      "translation": "to hear intelligently (often with implication of attention, obedience, etc.; causatively, to tell, etc.)"
    },
    {
      "surface": "אֶת",
      "lemma": "",
      "translit": "",
      "gloss": "",
      "morph": "HTo",
      "strong": "853",
      "index": 6,
      "resolved_lemma": "",
      "resolved_translit": "",
      "resolved_gloss": "properly, self (but generally used to point out more definitely the object of a verb or preposition, even or namely)",
      "translation": "properly, self (but generally used to point out more definitely the object of a verb or preposition, even or namely)"
    },
    {
      "surface": "אֶת",
      "lemma": "",
      "translit": "",
      "gloss": "",
      "morph": "HTo",
      "strong": "853",
      "index": 6,
      "resolved_lemma": "",
      "resolved_translit": "",
      "resolved_gloss": "properly, self (but generally used to point out more definitely the object of a verb or preposition, even or namely)",
      "translation": "properly, self (but generally used to point out more definitely the object of a verb or preposition, even or namely)"
    },
    {
      "surface": "ק֣וֹל",
      "lemma": "",
      "translit": "",
      "gloss": "",
      "morph": "HNcmsc",
      "strong": "6963 a",
      "index": 7,
      "resolved_lemma": "",
      "resolved_translit": "",
      "resolved_gloss": "a voice or sound",
      "translation": "a voice or sound"
    },
    {
      "surface": "ק֣וֹל",
      "lemma": "",
      "translit": "",
      "gloss": "",
      "morph": "HNcmsc",
      "strong": "6963 a",
      "index": 7,
      "resolved_lemma": "",
      "resolved_translit": "",
      "resolved_gloss": "a voice or sound",
      "translation": "a voice or sound"
    },
    {
      "surface": "דְּבָרָ֔י/ו",
      "lemma": "",
      "translit": "",
      "gloss": "",
      "morph": "HNcmpc/Sp3ms",
      "strong": "1697",
      "index": 8,
      "resolved_lemma": "",
      "resolved_translit": "",
      "resolved_gloss": "a word; by implication, a matter (as spoken of) or thing; adverbially, a cause",
      "translation": "a word; by implication, a matter (as spoken of) or thing; adverbially, a cause"
    },
    {
      "surface": "דְּבָרָ֔י/ו",
      "lemma": "",
      "translit": "",
      "gloss": "",
      "morph": "HNcmpc/Sp3ms",
      "strong": "1697",
      "index": 8,
      "resolved_lemma": "",
      "resolved_translit": "",
      "resolved_gloss": "a word; by implication, a matter (as spoken of) or thing; adverbially, a cause",
      "translation": "a word; by implication, a matter (as spoken of) or thing; adverbially, a cause"
    },
    {
      "surface": "וַ/אֲנִ֗י",
      "lemma": "",
      "translit": "",
      "gloss": "",
      "morph": "HC/Pp1cs",
      "strong": "c/589",
      "index": 9,
      "resolved_lemma": "",
      "resolved_translit": "",
      "resolved_gloss": "I",
      "translation": "I"
    },
    {
      "surface": "וַ/אֲנִ֗י",
      "lemma": "",
      "translit": "",
      "gloss": "",
      "morph": "HC/Pp1cs",
      "strong": "c/589",
      "index": 9,
      "resolved_lemma": "",
      "resolved_translit": "",
      "resolved_gloss": "I",
      "translation": "I"
    },
    {
      "surface": "הָיִ֛יתִי",
      "lemma": "",
      "translit": "",
      "gloss": "",
      "morph": "HVqp1cs",
      "strong": "1961",
      "index": 10,
      "resolved_lemma": "",
      "resolved_translit": "",
      "resolved_gloss": "to exist, i.e. be or become, come to pass (always emphatic, and not a mere copula or auxiliary)",
      "translation": "to exist, i.e. be or become, come to pass (always emphatic, and not a mere copula or auxiliary)"
    },
    {
      "surface": "הָיִ֛יתִי",
      "lemma": "",
      "translit": "",
      "gloss": "",
      "morph": "HVqp1cs",
      "strong": "1961",
      "index": 10,
      "resolved_lemma": "",
      "resolved_translit": "",
      "resolved_gloss": "to exist, i.e. be or become, come to pass (always emphatic, and not a mere copula or auxiliary)",
      "translation": "to exist, i.e. be or become, come to pass (always emphatic, and not a mere copula or auxiliary)"
    },
    {
      "surface": "נִרְדָּ֥ם",
      "lemma": "",
      "translit": "",
      "gloss": "",
      "morph": "HVNrmsa",
      "strong": "7290",
      "index": 11,
      "resolved_lemma": "",
      "resolved_translit": "",
      "resolved_gloss": "to stun, i.e. stupefy (with sleep or death)",
      "translation": "to stun, i.e. stupefy (with sleep or death)"
    },
    {
      "surface": "נִרְדָּ֥ם",
      "lemma": "",
      "translit": "",
      "gloss": "",
      "morph": "HVNrmsa",
      "strong": "7290",
      "index": 11,
      "resolved_lemma": "",
      "resolved_translit": "",
      "resolved_gloss": "to stun, i.e. stupefy (with sleep or death)",
      "translation": "to stun, i.e. stupefy (with sleep or death)"
    },
    {
      "surface": "עַל",
      "lemma": "",
      "translit": "",
      "gloss": "",
      "morph": "HR",
      "strong": "5921 a",
      "index": 12,
      "resolved_lemma": "",
      "resolved_translit": "",
      "resolved_gloss": "above, over, upon, or against (yet always in this last relation with a downward aspect) in a great variety of applications",
      "translation": "above, over, upon, or against (yet always in this last relation with a downward aspect) in a great variety of applications"
    },
    {
      "surface": "עַל",
      "lemma": "",
      "translit": "",
      "gloss": "",
      "morph": "HR",
      "strong": "5921 a",
      "index": 12,
      "resolved_lemma": "",
      "resolved_translit": "",
      "resolved_gloss": "above, over, upon, or against (yet always in this last relation with a downward aspect) in a great variety of applications",
      "translation": "above, over, upon, or against (yet always in this last relation with a downward aspect) in a great variety of applications"
    },
    {
      "surface": "פָּנַ֖/י",
      "lemma": "",
      "translit": "",
      "gloss": "",
      "morph": "HNcbpc/Sp1cs",
      "strong": "6440",
      "index": 13,
      "resolved_lemma": "",
      "resolved_translit": "",
      "resolved_gloss": "the face (as the part that turns); used in a great variety of applications (literally and figuratively); also (with prepositional prefix) as a preposition (before, etc.)",
      "translation": "the face (as the part that turns); used in a great variety of applications (literally and figuratively); also (with prepositional prefix) as a preposition (before, etc.)"
    },
    {
      "surface": "פָּנַ֖/י",
      "lemma": "",
      "translit": "",
      "gloss": "",
      "morph": "HNcbpc/Sp1cs",
      "strong": "6440",
      "index": 13,
      "resolved_lemma": "",
      "resolved_translit": "",
      "resolved_gloss": "the face (as the part that turns); used in a great variety of applications (literally and figuratively); also (with prepositional prefix) as a preposition (before, etc.)",
      "translation": "the face (as the part that turns); used in a great variety of applications (literally and figuratively); also (with prepositional prefix) as a preposition (before, etc.)"
    },
    {
      "surface": "וּ/פָנַ֥/י",
      "lemma": "",
      "translit": "",
      "gloss": "",
      "morph": "HC/Ncbpc/Sp1cs",
      "strong": "c/6440",
      "index": 14,
      "resolved_lemma": "",
      "resolved_translit": "",
      "resolved_gloss": "the face (as the part that turns); used in a great variety of applications (literally and figuratively); also (with prepositional prefix) as a preposition (before, etc.)",
      "translation": "the face (as the part that turns); used in a great variety of applications (literally and figuratively); also (with prepositional prefix) as a preposition (before, etc.)"
    },
    {
      "surface": "וּ/פָנַ֥/י",
      "lemma": "",
      "translit": "",
      "gloss": "",
      "morph": "HC/Ncbpc/Sp1cs",
      "strong": "c/6440",
      "index": 14,
      "resolved_lemma": "",
      "resolved_translit": "",
      "resolved_gloss": "the face (as the part that turns); used in a great variety of applications (literally and figuratively); also (with prepositional prefix) as a preposition (before, etc.)",
      "translation": "the face (as the part that turns); used in a great variety of applications (literally and figuratively); also (with prepositional prefix) as a preposition (before, etc.)"
    },
    {
      "surface": "אָֽרְצָ/ה",
      "lemma": "",
      "translit": "",
      "gloss": "",
      "morph": "HNcbsa/Sd",
      "strong": "776",
      "index": 15,
      "resolved_lemma": "",
      "resolved_translit": "",
      "resolved_gloss": "the earth (at large, or partitively a land)",
      "translation": "the earth (at large, or partitively a land)"
    },
    {
      "surface": "אָֽרְצָ/ה",
      "lemma": "",
      "translit": "",
      "gloss": "",
      "morph": "HNcbsa/Sd",
      "strong": "776",
      "index": 15,
      "resolved_lemma": "",
      "resolved_translit": "",
      "resolved_gloss": "the earth (at large, or partitively a land)",
      "translation": "the earth (at large, or partitively a land)"
    }
  ]
}