{
  "reference": "2KI 5:21",
  "book": "2KI",
  "book_code": "2KI",
  "chapter": 5,
  "verse": 21,
  "tokens": [
    {
      "surface": "וַ/יִּרְדֹּ֥ף",
      "lemma": "",
      "translit": "",
      "gloss": "",
      "morph": "HC/Vqw3ms",
      "strong": "c/7291",
      "index": 1,
      "resolved_lemma": "",
      "resolved_translit": "",
      "resolved_gloss": "to run after (usually with hostile intent; figuratively [of time] gone by)",
      "translation": "to run after (usually with hostile intent; figuratively [of time] gone by)"
    },
    {
      "surface": "וַ/יִּרְדֹּ֥ף",
      "lemma": "",
      "translit": "",
      "gloss": "",
      "morph": "HC/Vqw3ms",
      "strong": "c/7291",
      "index": 1,
      "resolved_lemma": "",
      "resolved_translit": "",
      "resolved_gloss": "to run after (usually with hostile intent; figuratively [of time] gone by)",
      "translation": "to run after (usually with hostile intent; figuratively [of time] gone by)"
    },
    {
      "surface": "גֵּיחֲזִ֖י",
      "lemma": "",
      "translit": "",
      "gloss": "",
      "morph": "HNp",
      "strong": "1522",
      "index": 2,
      "resolved_lemma": "",
      "resolved_translit": "",
      "resolved_gloss": "Gechazi, the servant of Elisha",
      "translation": "Gechazi, the servant of Elisha"
    },
    {
      "surface": "גֵּיחֲזִ֖י",
      "lemma": "",
      "translit": "",
      "gloss": "",
      "morph": "HNp",
      "strong": "1522",
      "index": 2,
      "resolved_lemma": "",
      "resolved_translit": "",
      "resolved_gloss": "Gechazi, the servant of Elisha",
      "translation": "Gechazi, the servant of Elisha"
    },
    {
      "surface": "אַחֲרֵ֣י",
      "lemma": "",
      "translit": "",
      "gloss": "",
      "morph": "HR",
      "strong": "310 a",
      "index": 3,
      "resolved_lemma": "",
      "resolved_translit": "",
      "resolved_gloss": "properly, the hind part; generally used as an adverb or conjunction, after (in various senses)",
      "translation": "properly, the hind part; generally used as an adverb or conjunction, after (in various senses)"
    },
    {
      "surface": "אַחֲרֵ֣י",
      "lemma": "",
      "translit": "",
      "gloss": "",
      "morph": "HR",
      "strong": "310 a",
      "index": 3,
      "resolved_lemma": "",
      "resolved_translit": "",
      "resolved_gloss": "properly, the hind part; generally used as an adverb or conjunction, after (in various senses)",
      "translation": "properly, the hind part; generally used as an adverb or conjunction, after (in various senses)"
    },
    {
      "surface": "נַֽעֲמָ֑ן",
      "lemma": "",
      "translit": "",
      "gloss": "",
      "morph": "HNp",
      "strong": "5283",
      "index": 4,
      "resolved_lemma": "",
      "resolved_translit": "",
      "resolved_gloss": "Naaman, the name of an Israelite and of a Damascene",
      "translation": "Naaman, the name of an Israelite and of a Damascene"
    },
    {
      "surface": "נַֽעֲמָ֑ן",
      "lemma": "",
      "translit": "",
      "gloss": "",
      "morph": "HNp",
      "strong": "5283",
      "index": 4,
      "resolved_lemma": "",
      "resolved_translit": "",
      "resolved_gloss": "Naaman, the name of an Israelite and of a Damascene",
      "translation": "Naaman, the name of an Israelite and of a Damascene"
    },
    {
      "surface": "וַ/יִּרְאֶ֤ה",
      "lemma": "",
      "translit": "",
      "gloss": "",
      "morph": "HC/Vqw3ms",
      "strong": "c/7200",
      "index": 5,
      "resolved_lemma": "",
      "resolved_translit": "",
      "resolved_gloss": "to see, literally or figuratively (in numerous applications, direct and implied, transitive, intransitive and causative)",
      "translation": "to see, literally or figuratively (in numerous applications, direct and implied, transitive, intransitive and causative)"
    },
    {
      "surface": "וַ/יִּרְאֶ֤ה",
      "lemma": "",
      "translit": "",
      "gloss": "",
      "morph": "HC/Vqw3ms",
      "strong": "c/7200",
      "index": 5,
      "resolved_lemma": "",
      "resolved_translit": "",
      "resolved_gloss": "to see, literally or figuratively (in numerous applications, direct and implied, transitive, intransitive and causative)",
      "translation": "to see, literally or figuratively (in numerous applications, direct and implied, transitive, intransitive and causative)"
    },
    {
      "surface": "נַֽעֲמָן֙",
      "lemma": "",
      "translit": "",
      "gloss": "",
      "morph": "HNp",
      "strong": "5283",
      "index": 6,
      "resolved_lemma": "",
      "resolved_translit": "",
      "resolved_gloss": "Naaman, the name of an Israelite and of a Damascene",
      "translation": "Naaman, the name of an Israelite and of a Damascene"
    },
    {
      "surface": "נַֽעֲמָן֙",
      "lemma": "",
      "translit": "",
      "gloss": "",
      "morph": "HNp",
      "strong": "5283",
      "index": 6,
      "resolved_lemma": "",
      "resolved_translit": "",
      "resolved_gloss": "Naaman, the name of an Israelite and of a Damascene",
      "translation": "Naaman, the name of an Israelite and of a Damascene"
    },
    {
      "surface": "רָ֣ץ",
      "lemma": "",
      "translit": "",
      "gloss": "",
      "morph": "HVqrmsa",
      "strong": "7323",
      "index": 7,
      "resolved_lemma": "",
      "resolved_translit": "",
      "resolved_gloss": "to run (for whatever reason, especially to rush)",
      "translation": "to run (for whatever reason, especially to rush)"
    },
    {
      "surface": "רָ֣ץ",
      "lemma": "",
      "translit": "",
      "gloss": "",
      "morph": "HVqrmsa",
      "strong": "7323",
      "index": 7,
      "resolved_lemma": "",
      "resolved_translit": "",
      "resolved_gloss": "to run (for whatever reason, especially to rush)",
      "translation": "to run (for whatever reason, especially to rush)"
    },
    {
      "surface": "אַחֲרָ֔י/ו",
      "lemma": "",
      "translit": "",
      "gloss": "",
      "morph": "HR/Sp3ms",
      "strong": "310 a",
      "index": 8,
      "resolved_lemma": "",
      "resolved_translit": "",
      "resolved_gloss": "properly, the hind part; generally used as an adverb or conjunction, after (in various senses)",
      "translation": "properly, the hind part; generally used as an adverb or conjunction, after (in various senses)"
    },
    {
      "surface": "אַחֲרָ֔י/ו",
      "lemma": "",
      "translit": "",
      "gloss": "",
      "morph": "HR/Sp3ms",
      "strong": "310 a",
      "index": 8,
      "resolved_lemma": "",
      "resolved_translit": "",
      "resolved_gloss": "properly, the hind part; generally used as an adverb or conjunction, after (in various senses)",
      "translation": "properly, the hind part; generally used as an adverb or conjunction, after (in various senses)"
    },
    {
      "surface": "וַ/יִּפֹּ֞ל",
      "lemma": "",
      "translit": "",
      "gloss": "",
      "morph": "HC/Vqw3ms",
      "strong": "c/5307",
      "index": 9,
      "resolved_lemma": "",
      "resolved_translit": "",
      "resolved_gloss": "to fall, in a great variety of applications (intransitive or causative, literal or figurative)",
      "translation": "to fall, in a great variety of applications (intransitive or causative, literal or figurative)"
    },
    {
      "surface": "וַ/יִּפֹּ֞ל",
      "lemma": "",
      "translit": "",
      "gloss": "",
      "morph": "HC/Vqw3ms",
      "strong": "c/5307",
      "index": 9,
      "resolved_lemma": "",
      "resolved_translit": "",
      "resolved_gloss": "to fall, in a great variety of applications (intransitive or causative, literal or figurative)",
      "translation": "to fall, in a great variety of applications (intransitive or causative, literal or figurative)"
    },
    {
      "surface": "מֵ/עַ֧ל",
      "lemma": "",
      "translit": "",
      "gloss": "",
      "morph": "HR/R",
      "strong": "m/5921 a",
      "index": 10,
      "resolved_lemma": "",
      "resolved_translit": "",
      "resolved_gloss": "above, over, upon, or against (yet always in this last relation with a downward aspect) in a great variety of applications",
      "translation": "above, over, upon, or against (yet always in this last relation with a downward aspect) in a great variety of applications"
    },
    {
      "surface": "מֵ/עַ֧ל",
      "lemma": "",
      "translit": "",
      "gloss": "",
      "morph": "HR/R",
      "strong": "m/5921 a",
      "index": 10,
      "resolved_lemma": "",
      "resolved_translit": "",
      "resolved_gloss": "above, over, upon, or against (yet always in this last relation with a downward aspect) in a great variety of applications",
      "translation": "above, over, upon, or against (yet always in this last relation with a downward aspect) in a great variety of applications"
    },
    {
      "surface": "הַ/מֶּרְכָּבָ֛ה",
      "lemma": "",
      "translit": "",
      "gloss": "",
      "morph": "HTd/Ncfsa",
      "strong": "d/4818",
      "index": 11,
      "resolved_lemma": "",
      "resolved_translit": "",
      "resolved_gloss": "a chariot",
      "translation": "a chariot"
    },
    {
      "surface": "הַ/מֶּרְכָּבָ֛ה",
      "lemma": "",
      "translit": "",
      "gloss": "",
      "morph": "HTd/Ncfsa",
      "strong": "d/4818",
      "index": 11,
      "resolved_lemma": "",
      "resolved_translit": "",
      "resolved_gloss": "a chariot",
      "translation": "a chariot"
    },
    {
      "surface": "לִ/קְרָאת֖/וֹ",
      "lemma": "",
      "translit": "",
      "gloss": "",
      "morph": "HR/Vqc/Sp3ms",
      "strong": "l/7125",
      "index": 12,
      "resolved_lemma": "",
      "resolved_translit": "",
      "resolved_gloss": "an encountering, accidental, friendly or hostile (also adverbially, opposite)",
      "translation": "an encountering, accidental, friendly or hostile (also adverbially, opposite)"
    },
    {
      "surface": "לִ/קְרָאת֖/וֹ",
      "lemma": "",
      "translit": "",
      "gloss": "",
      "morph": "HR/Vqc/Sp3ms",
      "strong": "l/7125",
      "index": 12,
      "resolved_lemma": "",
      "resolved_translit": "",
      "resolved_gloss": "an encountering, accidental, friendly or hostile (also adverbially, opposite)",
      "translation": "an encountering, accidental, friendly or hostile (also adverbially, opposite)"
    },
    {
      "surface": "וַ/יֹּ֥אמֶר",
      "lemma": "",
      "translit": "",
      "gloss": "",
      "morph": "HC/Vqw3ms",
      "strong": "c/559",
      "index": 13,
      "resolved_lemma": "",
      "resolved_translit": "",
      "resolved_gloss": "to say (used with great latitude)",
      "translation": "to say (used with great latitude)"
    },
    {
      "surface": "וַ/יֹּ֥אמֶר",
      "lemma": "",
      "translit": "",
      "gloss": "",
      "morph": "HC/Vqw3ms",
      "strong": "c/559",
      "index": 13,
      "resolved_lemma": "",
      "resolved_translit": "",
      "resolved_gloss": "to say (used with great latitude)",
      "translation": "to say (used with great latitude)"
    },
    {
      "surface": "הֲ/שָׁלֽוֹם",
      "lemma": "",
      "translit": "",
      "gloss": "",
      "morph": "HTi/Ncmsa",
      "strong": "i/7965",
      "index": 14,
      "resolved_lemma": "",
      "resolved_translit": "",
      "resolved_gloss": "safe, i.e. (figuratively) well, happy, friendly; also (abstractly) welfare, i.e. health, prosperity, peace",
      "translation": "safe, i.e. (figuratively) well, happy, friendly; also (abstractly) welfare, i.e. health, prosperity, peace"
    },
    {
      "surface": "הֲ/שָׁלֽוֹם",
      "lemma": "",
      "translit": "",
      "gloss": "",
      "morph": "HTi/Ncmsa",
      "strong": "i/7965",
      "index": 14,
      "resolved_lemma": "",
      "resolved_translit": "",
      "resolved_gloss": "safe, i.e. (figuratively) well, happy, friendly; also (abstractly) welfare, i.e. health, prosperity, peace",
      "translation": "safe, i.e. (figuratively) well, happy, friendly; also (abstractly) welfare, i.e. health, prosperity, peace"
    }
  ]
}